opendc/__init__.py
opendc/provider.py
opendc/utility.py
opendc/commands/__init__.py
opendc/commands/client.py
opendc/commands/config.py
opendc/commands/helm.py
opendc/commands/hosts.py
opendc/commands/init.py
opendc/commands/machine.py
opendc/commands/provision.py
opendc/commands/pull.py
opendc/commands/sol.py
opendc/commands/template.py
opendc/commands/up.py
opendc-0.0.21.data/data/opendc/LICENSE
opendc-0.0.21.data/data/opendc/ansible.cfg
opendc-0.0.21.data/data/opendc/site.yaml
opendc-0.0.21.data/data/opendc/charts/as1_artifact_storage/.helmignore
opendc-0.0.21.data/data/opendc/charts/as1_artifact_storage/Chart.yaml
opendc-0.0.21.data/data/opendc/charts/as1_artifact_storage/values.yaml
opendc-0.0.21.data/data/opendc/charts/cm1_cluster_management/.helmignore
opendc-0.0.21.data/data/opendc/charts/cm1_cluster_management/Chart.yaml
opendc-0.0.21.data/data/opendc/charts/cm1_cluster_management/values.yaml
opendc-0.0.21.data/data/opendc/charts/cm1_cluster_management/templates/k8s-dashboard-dp.yaml
opendc-0.0.21.data/data/opendc/charts/cm1_cluster_management/templates/k8s-dashboard-ingress.yaml
opendc-0.0.21.data/data/opendc/charts/cm1_cluster_management/templates/k8s-dashboard-svc.yaml
opendc-0.0.21.data/data/opendc/charts/cs1_cluster_services/.helmignore
opendc-0.0.21.data/data/opendc/charts/cs1_cluster_services/Chart.yaml
opendc-0.0.21.data/data/opendc/charts/cs1_cluster_services/values.yaml
opendc-0.0.21.data/data/opendc/charts/cs1_cluster_services/templates/k8s-dns-dp.yaml
opendc-0.0.21.data/data/opendc/charts/cs1_cluster_services/templates/k8s-dns-svc.yaml
opendc-0.0.21.data/data/opendc/charts/cs1_cluster_services/templates/k8s-heapster-dp.yaml
opendc-0.0.21.data/data/opendc/charts/cs1_cluster_services/templates/k8s-heapster-svc.yaml
opendc-0.0.21.data/data/opendc/charts/dbs1_distributed_block_storage/.helmignore
opendc-0.0.21.data/data/opendc/charts/dbs1_distributed_block_storage/Chart.yaml
opendc-0.0.21.dist-info/DESCRIPTION.rst
opendc-0.0.21.dist-info/METADATA
opendc-0.0.21.dist-info/RECORD
opendc-0.0.21.dist-info/WHEEL
opendc-0.0.21.dist-info/metadata.json
opendc-0.0.21.dist-info/top_level.txt
