Metadata-Version: 2.0
Name: opendc
Version: 0.0.21
Summary: opendc
Home-page: https://github.com/desdrury/opendc
Author: Des Drury
Author-email: des@drury-family.com
License: GNU General Public License v2 (GPLv2)
Keywords: opendc
Platform: UNKNOWN
Classifier: Development Status :: 3 - Alpha
Classifier: Environment :: Console
Classifier: Intended Audience :: System Administrators
Classifier: Intended Audience :: Developers
Classifier: License :: OSI Approved :: GNU General Public License v2 (GPLv2)
Classifier: Natural Language :: English
Classifier: Programming Language :: Python :: 2.7
Requires-Dist: ansible (==2.2.1.0)
Requires-Dist: docopt (>=0.6.2)
Requires-Dist: Jinja2 (>=2.8)
Requires-Dist: pprintpp (>=0.2.3)
